Workbook

Sheet Read Me
A1: NAV Oversight & Fund Accounting Pack
A2: Daily NAV production oversight and exception monitoring across a fund range
A5: PURPOSE
A6: This model reproduces the daily NAV oversight cycle an asset-servicing team runs:
A7: it recomputes each fund's NAV from raw accounting inputs and flags any strike that
A8: breaches tolerance or fails a data-quality check before the NAV is released.
A10: SHEETS
A11: Fund Master | B11: Reference data: fund codes, strategy, base currency, NAV tolerance (bps).
A12: Capital Activity | B12: Daily subscriptions and redemptions per fund.
A13: NAV Engine | B13: Core model. Recomputes NAV per share and runs the exception checks.
A14: Dashboard | B14: KPI summary and exception counts by type and by fund.
A16: COLOUR KEY
A17: Blue text | B17: Raw input, sourced from the fund accounting / custody feed.
A18: Black text | B18: Formula, computed by the model. Do not overwrite.
A20: EXCEPTION CHECKS
A21: NAV MOVE BREACH | B21: Day-over-day NAV per share move exceeds the fund's tolerance (bps).
A22: STALE PRICE | B22: Investments market value identical to prior day (non money-market).
A23: NEGATIVE CASH | B23: Cash balance is negative (overdrawn account).
A24: LARGE FLOW | B24: Net subscription/redemption exceeds 5% of net assets.
A26: NOTE | B26: All figures are synthetic and generated for portfolio demonstration only.

Sheet Fund Master
A1: FundCode | B1: FundName | C1: Strategy | D1: BaseCurrency | E1: StrikeFrequency | F1: NAVToleranceBps | G1: InceptionDate
A2: EQGL | B2: Global Equity Fund | C2: Equity | D2: USD | E2: Daily | F2: 500 | G2: 2019-03-15
A3: EQEM | B3: Emerging Markets Equity | C3: Equity | D3: USD | E3: Daily | F3: 500 | G3: 2020-06-01
A4: FIIG | B4: Investment Grade Bond | C4: Fixed Income | D4: USD | E4: Daily | F4: 150 | G4: 2017-01-10
A5: BALM | B5: Balanced Multi-Asset | C5: Balanced | D5: USD | E5: Daily | F5: 300 | G5: 2018-09-20
A6: MMUS | B6: USD Liquidity Fund | C6: Money Market | D6: USD | E6: Daily | F6: 10 | G6: 2015-04-02
A7: FDIV | B7: Global Dividend Fund | C7: Equity | D7: USD | E7: Daily | F7: 500 | G7: 2021-02-11

Sheet Capital Activity
A1: Date | B1: FundCode | C1: Subscriptions | D1: Redemptions | E1: NetFlow
A2: 2026-04-01 | B2: EQGL | C2: 383789.89 | D2: 336318.6 | E2: =C2-D2
A3: 2026-04-02 | B3: EQGL | C3: 213217.24 | D3: 178372.31 | E3: =C3-D3
A4: 2026-04-03 | B4: EQGL | C4: 0 | D4: 710316.68 | E4: =C4-D4
A5: 2026-04-06 | B5: EQGL | C5: 608240.98 | D5: 0 | E5: =C5-D5
A6: 2026-04-07 | B6: EQGL | C6: 111124.81 | D6: 297064.86 | E6: =C6-D6
A7: 2026-04-08 | B7: EQGL | C7: 1169973.4 | D7: 0 | E7: =C7-D7
A8: 2026-04-09 | B8: EQGL | C8: 1107419.1 | D8: 612873.17 | E8: =C8-D8
A9: 2026-04-10 | B9: EQGL | C9: 215284.75 | D9: 1216957.4 | E9: =C9-D9
A10: 2026-04-13 | B10: EQGL | C10: 54370.03 | D10: 913163.23 | E10: =C10-D10
A11: 2026-04-14 | B11: EQGL | C11: 804459.99 | D11: 1161321.8 | E11: =C11-D11
A12: 2026-04-15 | B12: EQGL | C12: 1162519.2 | D12: 1420955.7 | E12: =C12-D12
A13: 2026-04-16 | B13: EQGL | C13: 826878.33 | D13: 1544940.9 | E13: =C13-D13
... A385: 2026-06-30 | B385: FDIV | C385: 120789.48 | D385: 295685.56 | E385: =C385-D385

Sheet NAV Engine
A1: Date | B1: FundCode | C1: FundName | D1: Strategy | E1: InvestmentsMV | F1: Cash | G1: Receivables | H1: Payables | I1: AccruedMgmtFee | J1: SharesOutstanding | K1: TotalAssets | L1: TotalLiabilities | M1: NetAssets | N1: NAVPerShare | O1: PriorNAV | P1: NAVChangePct | Q1: ToleranceBps | R1: NetFlow | S1: BreachFlag | T1: StalePriceFlag | U1: NegCashFlag | V1: LargeFlowFlag | W1: FlagCount | X1: PrimaryException
A2: 2026-04-01 | B2: BALM | C2: =INDEX('Fund Master'!$B$2:$B$7,MATCH(B2,'Fund Master'!$A$2:$A$7,0)) | D2: =INDEX('Fund Master'!$C$2:$C$7,MATCH(B2,'Fund Master'!$A$2:$A$7,0)) | E2: 4.2821768e+08 | F2: 12506588 | G2: 2738059.6 | H2: 2244869.5 | I2: 10195.66 | J2: 23369565 | K2: =E2+F2+G2 | L2: =H2+I2 | M2: =K2-L2 | N2: =IFERROR(M2/J2,0) | O2: =IF((B2=B1),N1,"") | P2: =IF(O2="","",IFERROR((N2-O2)/O2,"")) | Q2: =INDEX('Fund Master'!$F$2:$F$7,MATCH(B2,'Fund Master'!$A$2:$A$7,0)) | R2: =SUMIFS('Capital Activity'!$E$2:$E$385,'Capital Activity'!$A$2:$A$385,A2,'Capital Activity'!$B$2:$B$385,B2) | S2: =IF(O2="","",IF(ABS(P2)*10000>Q2,"NAV MOVE BREACH","")) | T2: =IF(AND((B2=B1),D2<>"Money Market",E2=E1),"STALE PRICE","") | U2: =IF(F2<0,"NEGATIVE CASH","") | V2: =IF(ABS(R2)>0.05*M2,"LARGE FLOW","") | W2: =(S2<>"")*1+(T2<>"")*1+(U2<>"")*1+(V2<>"")*1 | X2: =IF(S2<>"",S2,IF(T2<>"",T2,IF(U2<>"",U2,IF(V2<>"",V2,""))))
A3: 2026-04-02 | B3: BALM | C3: =INDEX('Fund Master'!$B$2:$B$7,MATCH(B3,'Fund Master'!$A$2:$A$7,0)) | D3: =INDEX('Fund Master'!$C$2:$C$7,MATCH(B3,'Fund Master'!$A$2:$A$7,0)) | E3: 4.311621e+08 | F3: 12508550 | G3: 2498250.8 | H3: 2497369.5 | I3: 20461.42 | J3: 23369565 | K3: =E3+F3+G3 | L3: =H3+I3 | M3: =K3-L3 | N3: =IFERROR(M3/J3,0) | O3: =IF((B3=B2),N2,"") | P3: =IF(O3="","",IFERROR((N3-O3)/O3,"")) | Q3: =INDEX('Fund Master'!$F$2:$F$7,MATCH(B3,'Fund Master'!$A$2:$A$7,0)) | R3: =SUMIFS('Capital Activity'!$E$2:$E$385,'Capital Activity'!$A$2:$A$385,A3,'Capital Activity'!$B$2:$B$385,B3) | S3: =IF(O3="","",IF(ABS(P3)*10000>Q3,"NAV MOVE BREACH","")) | T3: =IF(AND((B3=B2),D3<>"Money Market",E3=E2),"STALE PRICE","") | U3: =IF(F3<0,"NEGATIVE CASH","") | V3: =IF(ABS(R3)>0.05*M3,"LARGE FLOW","") | W3: =(S3<>"")*1+(T3<>"")*1+(U3<>"")*1+(V3<>"")*1 | X3: =IF(S3<>"",S3,IF(T3<>"",T3,IF(U3<>"",U3,IF(V3<>"",V3,""))))
A4: 2026-04-03 | B4: BALM | C4: =INDEX('Fund Master'!$B$2:$B$7,MATCH(B4,'Fund Master'!$A$2:$A$7,0)) | D4: =INDEX('Fund Master'!$C$2:$C$7,MATCH(B4,'Fund Master'!$A$2:$A$7,0)) | E4: 4.3424641e+08 | F4: 13233702 | G4: 2660389.7 | H4: 2574004.5 | I4: 30800.62 | J4: 23369565 | K4: =E4+F4+G4 | L4: =H4+I4 | M4: =K4-L4 | N4: =IFERROR(M4/J4,0) | O4: =IF((B4=B3),N3,"") | P4: =IF(O4="","",IFERROR((N4-O4)/O4,"")) | Q4: =INDEX('Fund Master'!$F$2:$F$7,MATCH(B4,'Fund Master'!$A$2:$A$7,0)) | R4: =SUMIFS('Capital Activity'!$E$2:$E$385,'Capital Activity'!$A$2:$A$385,A4,'Capital Activity'!$B$2:$B$385,B4) | S4: =IF(O4="","",IF(ABS(P4)*10000>Q4,"NAV MOVE BREACH","")) | T4: =IF(AND((B4=B3),D4<>"Money Market",E4=E3),"STALE PRICE","") | U4: =IF(F4<0,"NEGATIVE CASH","") | V4: =IF(ABS(R4)>0.05*M4,"LARGE FLOW","") | W4: =(S4<>"")*1+(T4<>"")*1+(U4<>"")*1+(V4<>"")*1 | X4: =IF(S4<>"",S4,IF(T4<>"",T4,IF(U4<>"",U4,IF(V4<>"",V4,""))))
A5: 2026-04-06 | B5: BALM | C5: =INDEX('Fund Master'!$B$2:$B$7,MATCH(B5,'Fund Master'!$A$2:$A$7,0)) | D5: =INDEX('Fund Master'!$C$2:$C$7,MATCH(B5,'Fund Master'!$A$2:$A$7,0)) | E5: 4.3657428e+08 | F5: 13378301 | G5: 2685569.2 | H5: 2581244.6 | I5: 41195.25 | J5: 23369565 | K5: =E5+F5+G5 | L5: =H5+I5 | M5: =K5-L5 | N5: =IFERROR(M5/J5,0) | O5: =IF((B5=B4),N4,"") | P5: =IF(O5="","",IFERROR((N5-O5)/O5,"")) | Q5: =INDEX('Fund Master'!$F$2:$F$7,MATCH(B5,'Fund Master'!$A$2:$A$7,0)) | R5: =SUMIFS('Capital Activity'!$E$2:$E$385,'Capital Activity'!$A$2:$A$385,A5,'Capital Activity'!$B$2:$B$385,B5) | S5: =IF(O5="","",IF(ABS(P5)*10000>Q5,"NAV MOVE BREACH","")) | T5: =IF(AND((B5=B4),D5<>"Money Market",E5=E4),"STALE PRICE","") | U5: =IF(F5<0,"NEGATIVE CASH","") | V5: =IF(ABS(R5)>0.05*M5,"LARGE FLOW","") | W5: =(S5<>"")*1+(T5<>"")*1+(U5<>"")*1+(V5<>"")*1 | X5: =IF(S5<>"",S5,IF(T5<>"",T5,IF(U5<>"",U5,IF(V5<>"",V5,""))))
A6: 2026-04-07 | B6: BALM | C6: =INDEX('Fund Master'!$B$2:$B$7,MATCH(B6,'Fund Master'!$A$2:$A$7,0)) | D6: =INDEX('Fund Master'!$C$2:$C$7,MATCH(B6,'Fund Master'!$A$2:$A$7,0)) | E6: 4.3163571e+08 | F6: 13201496 | G6: 2552779.1 | H6: 2437721.7 | I6: 51472.29 | J6: 23369565 | K6: =E6+F6+G6 | L6: =H6+I6 | M6: =K6-L6 | N6: =IFERROR(M6/J6,0) | O6: =IF((B6=B5),N5,"") | P6: =IF(O6="","",IFERROR((N6-O6)/O6,"")) | Q6: =INDEX('Fund Master'!$F$2:$F$7,MATCH(B6,'Fund Master'!$A$2:$A$7,0)) | R6: =SUMIFS('Capital Activity'!$E$2:$E$385,'Capital Activity'!$A$2:$A$385,A6,'Capital Activity'!$B$2:$B$385,B6) | S6: =IF(O6="","",IF(ABS(P6)*10000>Q6,"NAV MOVE BREACH","")) | T6: =IF(AND((B6=B5),D6<>"Money Market",E6=E5),"STALE PRICE","") | U6: =IF(F6<0,"NEGATIVE CASH","") | V6: =IF(ABS(R6)>0.05*M6,"LARGE FLOW","") | W6: =(S6<>"")*1+(T6<>"")*1+(U6<>"")*1+(V6<>"")*1 | X6: =IF(S6<>"",S6,IF(T6<>"",T6,IF(U6<>"",U6,IF(V6<>"",V6,""))))
A7: 2026-04-08 | B7: BALM | C7: =INDEX('Fund Master'!$B$2:$B$7,MATCH(B7,'Fund Master'!$A$2:$A$7,0)) | D7: =INDEX('Fund Master'!$C$2:$C$7,MATCH(B7,'Fund Master'!$A$2:$A$7,0)) | E7: 4.3441741e+08 | F7: 12877222 | G7: 2466051.8 | H7: 2551516.7 | I7: 61815.56 | J7: 23369565 | K7: =E7+F7+G7 | L7: =H7+I7 | M7: =K7-L7 | N7: =IFERROR(M7/J7,0) | O7: =IF((B7=B6),N6,"") | P7: =IF(O7="","",IFERROR((N7-O7)/O7,"")) | Q7: =INDEX('Fund Master'!$F$2:$F$7,MATCH(B7,'Fund Master'!$A$2:$A$7,0)) | R7: =SUMIFS('Capital Activity'!$E$2:$E$385,'Capital Activity'!$A$2:$A$385,A7,'Capital Activity'!$B$2:$B$385,B7) | S7: =IF(O7="","",IF(ABS(P7)*10000>Q7,"NAV MOVE BREACH","")) | T7: =IF(AND((B7=B6),D7<>"Money Market",E7=E6),"STALE PRICE","") | U7: =IF(F7<0,"NEGATIVE CASH","") | V7: =IF(ABS(R7)>0.05*M7,"LARGE FLOW","") | W7: =(S7<>"")*1+(T7<>"")*1+(U7<>"")*1+(V7<>"")*1 | X7: =IF(S7<>"",S7,IF(T7<>"",T7,IF(U7<>"",U7,IF(V7<>"",V7,""))))
A8: 2026-04-09 | B8: BALM | C8: =INDEX('Fund Master'!$B$2:$B$7,MATCH(B8,'Fund Master'!$A$2:$A$7,0)) | D8: =INDEX('Fund Master'!$C$2:$C$7,MATCH(B8,'Fund Master'!$A$2:$A$7,0)) | E8: 4.3612917e+08 | F8: 12674569 | G8: 2486798.7 | H8: 2421936.8 | I8: 72199.59 | J8: 23369565 | K8: =E8+F8+G8 | L8: =H8+I8 | M8: =K8-L8 | N8: =IFERROR(M8/J8,0) | O8: =IF((B8=B7),N7,"") | P8: =IF(O8="","",IFERROR((N8-O8)/O8,"")) | Q8: =INDEX('Fund Master'!$F$2:$F$7,MATCH(B8,'Fund Master'!$A$2:$A$7,0)) | R8: =SUMIFS('Capital Activity'!$E$2:$E$385,'Capital Activity'!$A$2:$A$385,A8,'Capital Activity'!$B$2:$B$385,B8) | S8: =IF(O8="","",IF(ABS(P8)*10000>Q8,"NAV MOVE BREACH","")) | T8: =IF(AND((B8=B7),D8<>"Money Market",E8=E7),"STALE PRICE","") | U8: =IF(F8<0,"NEGATIVE CASH","") | V8: =IF(ABS(R8)>0.05*M8,"LARGE FLOW","") | W8: =(S8<>"")*1+(T8<>"")*1+(U8<>"")*1+(V8<>"")*1 | X8: =IF(S8<>"",S8,IF(T8<>"",T8,IF(U8<>"",U8,IF(V8<>"",V8,""))))
A9: 2026-04-10 | B9: BALM | C9: =INDEX('Fund Master'!$B$2:$B$7,MATCH(B9,'Fund Master'!$A$2:$A$7,0)) | D9: =INDEX('Fund Master'!$C$2:$C$7,MATCH(B9,'Fund Master'!$A$2:$A$7,0)) | E9: 4.3149208e+08 | F9: 12653845 | G9: 2458324.5 | H9: 2453400.7 | I9: 82473.21 | J9: 23369565 | K9: =E9+F9+G9 | L9: =H9+I9 | M9: =K9-L9 | N9: =IFERROR(M9/J9,0) | O9: =IF((B9=B8),N8,"") | P9: =IF(O9="","",IFERROR((N9-O9)/O9,"")) | Q9: =INDEX('Fund Master'!$F$2:$F$7,MATCH(B9,'Fund Master'!$A$2:$A$7,0)) | R9: =SUMIFS('Capital Activity'!$E$2:$E$385,'Capital Activity'!$A$2:$A$385,A9,'Capital Activity'!$B$2:$B$385,B9) | S9: =IF(O9="","",IF(ABS(P9)*10000>Q9,"NAV MOVE BREACH","")) | T9: =IF(AND((B9=B8),D9<>"Money Market",E9=E8),"STALE PRICE","") | U9: =IF(F9<0,"NEGATIVE CASH","") | V9: =IF(ABS(R9)>0.05*M9,"LARGE FLOW","") | W9: =(S9<>"")*1+(T9<>"")*1+(U9<>"")*1+(V9<>"")*1 | X9: =IF(S9<>"",S9,IF(T9<>"",T9,IF(U9<>"",U9,IF(V9<>"",V9,""))))
A10: 2026-04-13 | B10: BALM | C10: =INDEX('Fund Master'!$B$2:$B$7,MATCH(B10,'Fund Master'!$A$2:$A$7,0)) | D10: =INDEX('Fund Master'!$C$2:$C$7,MATCH(B10,'Fund Master'!$A$2:$A$7,0)) | E10: 4.3194581e+08 | F10: 12555863 | G10: 2473587.7 | H10: 2512302.6 | I10: 92757.63 | J10: 23369565 | K10: =E10+F10+G10 | L10: =H10+I10 | M10: =K10-L10 | N10: =IFERROR(M10/J10,0) | O10: =IF((B10=B9),N9,"") | P10: =IF(O10="","",IFERROR((N10-O10)/O10,"")) | Q10: =INDEX('Fund Master'!$F$2:$F$7,MATCH(B10,'Fund Master'!$A$2:$A$7,0)) | R10: =SUMIFS('Capital Activity'!$E$2:$E$385,'Capital Activity'!$A$2:$A$385,A10,'Capital Activity'!$B$2:$B$385,B10) | S10: =IF(O10="","",IF(ABS(P10)*10000>Q10,"NAV MOVE BREACH","")) | T10: =IF(AND((B10=B9),D10<>"Money Market",E10=E9),"STALE PRICE","") | U10: =IF(F10<0,"NEGATIVE CASH","") | V10: =IF(ABS(R10)>0.05*M10,"LARGE FLOW","") | W10: =(S10<>"")*1+(T10<>"")*1+(U10<>"")*1+(V10<>"")*1 | X10: =IF(S10<>"",S10,IF(T10<>"",T10,IF(U10<>"",U10,IF(V10<>"",V10,""))))
A11: 2026-04-14 | B11: BALM | C11: =INDEX('Fund Master'!$B$2:$B$7,MATCH(B11,'Fund Master'!$A$2:$A$7,0)) | D11: =INDEX('Fund Master'!$C$2:$C$7,MATCH(B11,'Fund Master'!$A$2:$A$7,0)) | E11: 4.2997029e+08 | F11: 12327422 | G11: 2317535.8 | H11: 2681356.3 | I11: 102995.02 | J11: 23369565 | K11: =E11+F11+G11 | L11: =H11+I11 | M11: =K11-L11 | N11: =IFERROR(M11/J11,0) | O11: =IF((B11=B10),N10,"") | P11: =IF(O11="","",IFERROR((N11-O11)/O11,"")) | Q11: =INDEX('Fund Master'!$F$2:$F$7,MATCH(B11,'Fund Master'!$A$2:$A$7,0)) | R11: =SUMIFS('Capital Activity'!$E$2:$E$385,'Capital Activity'!$A$2:$A$385,A11,'Capital Activity'!$B$2:$B$385,B11) | S11: =IF(O11="","",IF(ABS(P11)*10000>Q11,"NAV MOVE BREACH","")) | T11: =IF(AND((B11=B10),D11<>"Money Market",E11=E10),"STALE PRICE","") | U11: =IF(F11<0,"NEGATIVE CASH","") | V11: =IF(ABS(R11)>0.05*M11,"LARGE FLOW","") | W11: =(S11<>"")*1+(T11<>"")*1+(U11<>"")*1+(V11<>"")*1 | X11: =IF(S11<>"",S11,IF(T11<>"",T11,IF(U11<>"",U11,IF(V11<>"",V11,""))))
A12: 2026-04-15 | B12: BALM | C12: =INDEX('Fund Master'!$B$2:$B$7,MATCH(B12,'Fund Master'!$A$2:$A$7,0)) | D12: =INDEX('Fund Master'!$C$2:$C$7,MATCH(B12,'Fund Master'!$A$2:$A$7,0)) | E12: 4.279558e+08 | F12: 12499459 | G12: 2276383.6 | H12: 2796948.5 | I12: 113184.45 | J12: 23369565 | K12: =E12+F12+G12 | L12: =H12+I12 | M12: =K12-L12 | N12: =IFERROR(M12/J12,0) | O12: =IF((B12=B11),N11,"") | P12: =IF(O12="","",IFERROR((N12-O12)/O12,"")) | Q12: =INDEX('Fund Master'!$F$2:$F$7,MATCH(B12,'Fund Master'!$A$2:$A$7,0)) | R12: =SUMIFS('Capital Activity'!$E$2:$E$385,'Capital Activity'!$A$2:$A$385,A12,'Capital Activity'!$B$2:$B$385,B12) | S12: =IF(O12="","",IF(ABS(P12)*10000>Q12,"NAV MOVE BREACH","")) | T12: =IF(AND((B12=B11),D12<>"Money Market",E12=E11),"STALE PRICE","") | U12: =IF(F12<0,"NEGATIVE CASH","") | V12: =IF(ABS(R12)>0.05*M12,"LARGE FLOW","") | W12: =(S12<>"")*1+(T12<>"")*1+(U12<>"")*1+(V12<>"")*1 | X12: =IF(S12<>"",S12,IF(T12<>"",T12,IF(U12<>"",U12,IF(V12<>"",V12,""))))
A13: 2026-04-16 | B13: BALM | C13: =INDEX('Fund Master'!$B$2:$B$7,MATCH(B13,'Fund Master'!$A$2:$A$7,0)) | D13: =INDEX('Fund Master'!$C$2:$C$7,MATCH(B13,'Fund Master'!$A$2:$A$7,0)) | E13: 4.2561045e+08 | F13: 12978756 | G13: 2142599.2 | H13: 2813267.3 | I13: 123318.03 | J13: 23369565 | K13: =E13+F13+G13 | L13: =H13+I13 | M13: =K13-L13 | N13: =IFERROR(M13/J13,0) | O13: =IF((B13=B12),N12,"") | P13: =IF(O13="","",IFERROR((N13-O13)/O13,"")) | Q13: =INDEX('Fund Master'!$F$2:$F$7,MATCH(B13,'Fund Master'!$A$2:$A$7,0)) | R13: =SUMIFS('Capital Activity'!$E$2:$E$385,'Capital Activity'!$A$2:$A$385,A13,'Capital Activity'!$B$2:$B$385,B13) | S13: =IF(O13="","",IF(ABS(P13)*10000>Q13,"NAV MOVE BREACH","")) | T13: =IF(AND((B13=B12),D13<>"Money Market",E13=E12),"STALE PRICE","") | U13: =IF(F13<0,"NEGATIVE CASH","") | V13: =IF(ABS(R13)>0.05*M13,"LARGE FLOW","") | W13: =(S13<>"")*1+(T13<>"")*1+(U13<>"")*1+(V13<>"")*1 | X13: =IF(S13<>"",S13,IF(T13<>"",T13,IF(U13<>"",U13,IF(V13<>"",V13,""))))
... A385: 2026-06-30 | B385: MMUS | C385: =INDEX('Fund Master'!$B$2:$B$7,MATCH(B385,'Fund Master'!$A$2:$A$7,0)) | D385: =INDEX('Fund Master'!$C$2:$C$7,MATCH(B385,'Fund Master'!$A$2:$A$7,0)) | E385: 8.1267452e+08 | F385: 24708739 | G385: 4815577.4 | H385: 4195347.6 | I385: 371018.58 | J385: 810000000 | K385: =E385+F385+G385 | L385: =H385+I385 | M385: =K385-L385 | N385: =IFERROR(M385/J385,0) | O385: =IF((B385=B384),N384,"") | P385: =IF(O385="","",IFERROR((N385-O385)/O385,"")) | Q385: =INDEX('Fund Master'!$F$2:$F$7,MATCH(B385,'Fund Master'!$A$2:$A$7,0)) | R385: =SUMIFS('Capital Activity'!$E$2:$E$385,'Capital Activity'!$A$2:$A$385,A385,'Capital Activity'!$B$2:$B$385,B385) | S385: =IF(O385="","",IF(ABS(P385)*10000>Q385,"NAV MOVE BREACH","")) | T385: =IF(AND((B385=B384),D385<>"Money Market",E385=E384),"STALE PRICE","") | U385: =IF(F385<0,"NEGATIVE CASH","") | V385: =IF(ABS(R385)>0.05*M385,"LARGE FLOW","") | W385: =(S385<>"")*1+(T385<>"")*1+(U385<>"")*1+(V385<>"")*1 | X385: =IF(S385<>"",S385,IF(T385<>"",T385,IF(U385<>"",U385,IF(V385<>"",V385,""))))

Sheet Dashboard
A1: NAV Oversight Dashboard
A2: Reporting period: 01 Apr 2026 to 30 Jun 2026 | 6 funds | daily strike
A4: Fund strikes reviewed | C4: Total exceptions | E4: NAV move breaches | G4: Total net assets ($)
A5: =COUNTA('NAV Engine'!$B$2:$B$385) | C5: =SUM('NAV Engine'!$W$2:$W$385) | E5: =COUNTIF('NAV Engine'!$S$2:$S$385,"NAV MOVE BREACH") | G5: =SUMIFS('NAV Engine'!$M$2:$M$385,'NAV Engine'!$A$2:$A$385,MAX('NAV Engine'!$A$2:$A$385))
A8: Exceptions by type | D8: Exceptions by fund
A9: Type | B9: Count | D9: Fund | E9: Net Assets | F9: Exceptions
A10: NAV MOVE BREACH | B10: =COUNTIF('NAV Engine'!$S$2:$S$385,"NAV MOVE BREACH") | D10: EQGL | E10: =SUMIFS('NAV Engine'!$M$2:$M$385,'NAV Engine'!$B$2:$B$385,D10,'NAV Engine'!$A$2:$A$385,MAX('NAV Engine'!$A$2:$A$385)) | F10: =SUMIFS('NAV Engine'!$W$2:$W$385,'NAV Engine'!$B$2:$B$385,D10)
A11: STALE PRICE | B11: =COUNTIF('NAV Engine'!$T$2:$T$385,"STALE PRICE") | D11: EQEM | E11: =SUMIFS('NAV Engine'!$M$2:$M$385,'NAV Engine'!$B$2:$B$385,D11,'NAV Engine'!$A$2:$A$385,MAX('NAV Engine'!$A$2:$A$385)) | F11: =SUMIFS('NAV Engine'!$W$2:$W$385,'NAV Engine'!$B$2:$B$385,D11)
A12: NEGATIVE CASH | B12: =COUNTIF('NAV Engine'!$U$2:$U$385,"NEGATIVE CASH") | D12: FIIG | E12: =SUMIFS('NAV Engine'!$M$2:$M$385,'NAV Engine'!$B$2:$B$385,D12,'NAV Engine'!$A$2:$A$385,MAX('NAV Engine'!$A$2:$A$385)) | F12: =SUMIFS('NAV Engine'!$W$2:$W$385,'NAV Engine'!$B$2:$B$385,D12)
A13: LARGE FLOW | B13: =COUNTIF('NAV Engine'!$V$2:$V$385,"LARGE FLOW") | D13: BALM | E13: =SUMIFS('NAV Engine'!$M$2:$M$385,'NAV Engine'!$B$2:$B$385,D13,'NAV Engine'!$A$2:$A$385,MAX('NAV Engine'!$A$2:$A$385)) | F13: =SUMIFS('NAV Engine'!$W$2:$W$385,'NAV Engine'!$B$2:$B$385,D13)
D14: MMUS | E14: =SUMIFS('NAV Engine'!$M$2:$M$385,'NAV Engine'!$B$2:$B$385,D14,'NAV Engine'!$A$2:$A$385,MAX('NAV Engine'!$A$2:$A$385)) | F14: =SUMIFS('NAV Engine'!$W$2:$W$385,'NAV Engine'!$B$2:$B$385,D14)
D15: FDIV | E15: =SUMIFS('NAV Engine'!$M$2:$M$385,'NAV Engine'!$B$2:$B$385,D15,'NAV Engine'!$A$2:$A$385,MAX('NAV Engine'!$A$2:$A$385)) | F15: =SUMIFS('NAV Engine'!$W$2:$W$385,'NAV Engine'!$B$2:$B$385,D15)
