Workbook

Sheet Read Me
A1: Cash & Position Reconciliation
A2: Daily internal-book vs custodian reconciliation with break aging and exception workflow
A5: PURPOSE
A6: Reconciles the fund accountant's internal book of record against the custodian
A7: statement position by position and cash by cash, classifies every mismatch, and
A8: ages each open break so the oldest exposures surface first.
A10: SHEETS
A11: Parameters | B11: As-of date and matching tolerances (price bps, market-value).
A12: Internal Book | B12: Positions and cash per the internal accounting system.
A13: Custodian Statement | B13: Positions and cash per the custodian feed.
A14: Reconciliation | B14: Matching engine. One row per position, break type, aging, status.
A15: Break Register | B15: Analyst workflow: first-identified date, status, comment per break.
A16: Dashboard | B16: Match rate, break exposure, breaks by type / fund, aging profile.
A18: BREAK TYPES
A19: MISSING IN INTERNAL | B19: At custodian, not in the internal book (unbooked trade or corp action).
A20: MISSING IN CUSTODIAN | B20: In the internal book, not at custodian (failed / unsettled trade).
A21: QUANTITY BREAK | B21: Both sides hold it, quantities differ (settlement timing).
A22: PRICE BREAK | B22: Same quantity, price differs beyond the bps tolerance (stale price).
A23: CASH BREAK | B23: Cash balance differs between the book and the custodian.
A24: MV BREAK | B24: Residual market-value difference beyond tolerance.
A26: NOTE | B26: All figures are synthetic and generated for portfolio demonstration only.

Sheet Parameters
A1: Parameter | B1: Value
A2: AsOfDate | B2: 46203
A3: PriceTolBps | B3: 10
A4: MVTol | B4: 1

Sheet Internal Book
A1: Fund | B1: SecurityID | C1: SecurityName | D1: AssetClass | E1: Quantity | F1: Price | G1: MarketValue | H1: Key
A2: EQGL | B2: EQ0023 | C2: Global Equity Holding 03 | D2: Equity | E2: 21251 | F2: 150.81 | G2: =E2*F2 | H2: =A2&"|"&B2
A3: EQGL | B3: EQ0028 | C3: Global Equity Holding 08 | D3: Equity | E3: 27067 | F3: 460.85 | G3: =E3*F3 | H3: =A3&"|"&B3
A4: EQGL | B4: EQ0035 | C4: Global Equity Holding 15 | D4: Equity | E4: 11184 | F4: 89.94 | G4: =E4*F4 | H4: =A4&"|"&B4
A5: EQGL | B5: EQ0016 | C5: TSMC ADR | D5: Equity | E5: 5468 | F5: 273.99 | G5: =E5*F5 | H5: =A5&"|"&B5
A6: EQGL | B6: EQ0019 | C6: JPMorgan Chase | D6: Equity | E6: 18957 | F6: 153.64 | G6: =E6*F6 | H6: =A6&"|"&B6
A7: EQGL | B7: EQ0030 | C7: Global Equity Holding 10 | D7: Equity | E7: 55299 | F7: 222.17 | G7: =E7*F7 | H7: =A7&"|"&B7
A8: EQGL | B8: EQ0033 | C8: Global Equity Holding 13 | D8: Equity | E8: 25416 | F8: 473.73 | G8: =E8*F8 | H8: =A8&"|"&B8
A9: EQGL | B9: EQ0031 | C9: Global Equity Holding 11 | D9: Equity | E9: 47717 | F9: 181.2 | G9: =E9*F9 | H9: =A9&"|"&B9
A10: EQGL | B10: EQ0011 | C10: SAP SE | D10: Equity | E10: 18370 | F10: 254.3 | G10: =E10*F10 | H10: =A10&"|"&B10
A11: EQGL | B11: EQ0002 | C11: Microsoft Corp | D11: Equity | E11: 37583 | F11: 323.92 | G11: =E11*F11 | H11: =A11&"|"&B11
A12: EQGL | B12: EQ0042 | C12: Global Equity Holding 22 | D12: Equity | E12: 15918 | F12: 209.37 | G12: =E12*F12 | H12: =A12&"|"&B12
A13: EQGL | B13: EQ0014 | C13: Siemens AG | D13: Equity | E13: 40202 | F13: 224.97 | G13: =E13*F13 | H13: =A13&"|"&B13
... A125: MMUS | B125: CASH_USD_MMUS | C125: USD Cash | D125: Cash | E125: 2444128.9 | F125: 1 | G125: =E125*F125 | H125: =A125&"|"&B125

Sheet Custodian Statement
A1: Fund | B1: SecurityID | C1: SecurityName | D1: AssetClass | E1: Quantity | F1: Price | G1: MarketValue | H1: Key
A2: EQGL | B2: EQ0023 | C2: Global Equity Holding 03 | D2: Equity | E2: 21251 | F2: 150.81 | G2: =E2*F2 | H2: =A2&"|"&B2
A3: EQGL | B3: EQ0028 | C3: Global Equity Holding 08 | D3: Equity | E3: 27067 | F3: 460.85 | G3: =E3*F3 | H3: =A3&"|"&B3
A4: EQGL | B4: EQ0035 | C4: Global Equity Holding 15 | D4: Equity | E4: 11184 | F4: 89.94 | G4: =E4*F4 | H4: =A4&"|"&B4
A5: EQGL | B5: EQ0016 | C5: TSMC ADR | D5: Equity | E5: 5468 | F5: 273.99 | G5: =E5*F5 | H5: =A5&"|"&B5
A6: EQGL | B6: EQ0019 | C6: JPMorgan Chase | D6: Equity | E6: 18957 | F6: 153.64 | G6: =E6*F6 | H6: =A6&"|"&B6
A7: EQGL | B7: EQ0030 | C7: Global Equity Holding 10 | D7: Equity | E7: 55299 | F7: 222.17 | G7: =E7*F7 | H7: =A7&"|"&B7
A8: EQGL | B8: EQ0033 | C8: Global Equity Holding 13 | D8: Equity | E8: 25416 | F8: 473.73 | G8: =E8*F8 | H8: =A8&"|"&B8
A9: EQGL | B9: EQ0031 | C9: Global Equity Holding 11 | D9: Equity | E9: 47717 | F9: 181.2 | G9: =E9*F9 | H9: =A9&"|"&B9
A10: EQGL | B10: EQ0011 | C10: SAP SE | D10: Equity | E10: 18370 | F10: 254.3 | G10: =E10*F10 | H10: =A10&"|"&B10
A11: EQGL | B11: EQ0002 | C11: Microsoft Corp | D11: Equity | E11: 37583 | F11: 323.92 | G11: =E11*F11 | H11: =A11&"|"&B11
A12: EQGL | B12: EQ0042 | C12: Global Equity Holding 22 | D12: Equity | E12: 15918 | F12: 209.37 | G12: =E12*F12 | H12: =A12&"|"&B12
A13: EQGL | B13: EQ0014 | C13: Siemens AG | D13: Equity | E13: 40202 | F13: 224.97 | G13: =E13*F13 | H13: =A13&"|"&B13
... A125: EQGL | B125: EQ0001 | C125: Apple Inc | D125: Equity | E125: 56458 | F125: 69.42 | G125: =E125*F125 | H125: =A125&"|"&B125

Sheet Break Register
A1: Key | B1: FirstIdentified | C1: Status | D1: Comment
A2: EQGL|ET0081 | B2: 46199 | C2: Open | D2: Unsettled trade - qty mismatch
A3: BALM|EQ0047 | B3: 46194 | C3: Investigating | D3: Unsettled trade - qty mismatch
A4: FIIG|BD0053 | B4: 46197 | C4: Open | D4: Stale price - custodian vs vendor
A5: BALM|BD0058 | B5: 46188 | C5: Investigating | D5: Stale price - custodian vs vendor
A6: EQGL|EQ0034 | B6: 46201 | C6: Open | D6: Position missing at custodian
A7: MMUS|BD0068 | B7: 46170 | C7: Investigating | D7: Position missing at custodian
A8: BALM|EQ0005 | B8: 46200 | C8: Open | D8: Unbooked position - internal missing
A9: EQGL|EQ0001 | B9: 46191 | C9: Open | D9: Unbooked position - internal missing
A10: FIIG|CASH_USD_FIIG | B10: 46198 | C10: Open | D10: Unreconciled cash movement

Sheet Reconciliation
A1: Fund | B1: SecurityID | C1: SecurityName | D1: AssetClass | E1: Key | F1: IntQty | G1: IntPrice | H1: IntMV | I1: CustQty | J1: CustPrice | K1: CustMV | L1: QtyDiff | M1: MVDiff | N1: PriceDiffBps | O1: InInternal | P1: InCustodian | Q1: BreakType | R1: FirstIdentified | S1: DaysOpen | T1: AgeBucket | U1: Status | V1: AbsMVDiff | W1: IsBreak
A2: BALM | B2: BD0052 | C2: US Treasury 3.0% 2033 | D2: Bond | E2: =A2&"|"&B2 | F2: =IFERROR(INDEX('Internal Book'!$E$2:$E$125,MATCH(E2,'Internal Book'!$H$2:$H$125,0)),0) | G2: =IFERROR(INDEX('Internal Book'!$F$2:$F$125,MATCH(E2,'Internal Book'!$H$2:$H$125,0)),0) | H2: =IFERROR(INDEX('Internal Book'!$G$2:$G$125,MATCH(E2,'Internal Book'!$H$2:$H$125,0)),0) | I2: =IFERROR(INDEX('Custodian Statement'!$E$2:$E$125,MATCH(E2,'Custodian Statement'!$H$2:$H$125,0)),0) | J2: =IFERROR(INDEX('Custodian Statement'!$F$2:$F$125,MATCH(E2,'Custodian Statement'!$H$2:$H$125,0)),0) | K2: =IFERROR(INDEX('Custodian Statement'!$G$2:$G$125,MATCH(E2,'Custodian Statement'!$H$2:$H$125,0)),0) | L2: =F2-I2 | M2: =H2-K2 | N2: =IFERROR((G2-J2)/J2*10000,0) | O2: =COUNTIF('Internal Book'!$H$2:$H$125,E2) | P2: =COUNTIF('Custodian Statement'!$H$2:$H$125,E2) | Q2: =IF(O2=0,"MISSING IN INTERNAL",IF(P2=0,"MISSING IN CUSTODIAN",IF(AND(D2="Cash",ABS(M2)>Parameters!$B$4),"CASH BREAK",IF(L2<>0,"QUANTITY BREAK",IF(ABS(N2)>Parameters!$B$3,"PRICE BREAK",IF(ABS(M2)>Parameters!$B$4,"MV BREAK","MATCHED")))))) | R2: =IFERROR(INDEX('Break Register'!$B$2:$B$10,MATCH(E2,'Break Register'!$A$2:$A$10,0)),"") | S2: =IF(R2="","",Parameters!$B$2-R2) | T2: =IF(S2="","",IF(S2<=2,"0-2 days",IF(S2<=5,"3-5 days",IF(S2<=10,"6-10 days",IF(S2<=30,"11-30 days","30+ days"))))) | U2: =IFERROR(INDEX('Break Register'!$C$2:$C$10,MATCH(E2,'Break Register'!$A$2:$A$10,0)),"") | V2: =ABS(M2) | W2: =IF(Q2="MATCHED",0,1)
A3: BALM | B3: BD0055 | C3: Apple 3.35% 2029 | D3: Bond | E3: =A3&"|"&B3 | F3: =IFERROR(INDEX('Internal Book'!$E$2:$E$125,MATCH(E3,'Internal Book'!$H$2:$H$125,0)),0) | G3: =IFERROR(INDEX('Internal Book'!$F$2:$F$125,MATCH(E3,'Internal Book'!$H$2:$H$125,0)),0) | H3: =IFERROR(INDEX('Internal Book'!$G$2:$G$125,MATCH(E3,'Internal Book'!$H$2:$H$125,0)),0) | I3: =IFERROR(INDEX('Custodian Statement'!$E$2:$E$125,MATCH(E3,'Custodian Statement'!$H$2:$H$125,0)),0) | J3: =IFERROR(INDEX('Custodian Statement'!$F$2:$F$125,MATCH(E3,'Custodian Statement'!$H$2:$H$125,0)),0) | K3: =IFERROR(INDEX('Custodian Statement'!$G$2:$G$125,MATCH(E3,'Custodian Statement'!$H$2:$H$125,0)),0) | L3: =F3-I3 | M3: =H3-K3 | N3: =IFERROR((G3-J3)/J3*10000,0) | O3: =COUNTIF('Internal Book'!$H$2:$H$125,E3) | P3: =COUNTIF('Custodian Statement'!$H$2:$H$125,E3) | Q3: =IF(O3=0,"MISSING IN INTERNAL",IF(P3=0,"MISSING IN CUSTODIAN",IF(AND(D3="Cash",ABS(M3)>Parameters!$B$4),"CASH BREAK",IF(L3<>0,"QUANTITY BREAK",IF(ABS(N3)>Parameters!$B$3,"PRICE BREAK",IF(ABS(M3)>Parameters!$B$4,"MV BREAK","MATCHED")))))) | R3: =IFERROR(INDEX('Break Register'!$B$2:$B$10,MATCH(E3,'Break Register'!$A$2:$A$10,0)),"") | S3: =IF(R3="","",Parameters!$B$2-R3) | T3: =IF(S3="","",IF(S3<=2,"0-2 days",IF(S3<=5,"3-5 days",IF(S3<=10,"6-10 days",IF(S3<=30,"11-30 days","30+ days"))))) | U3: =IFERROR(INDEX('Break Register'!$C$2:$C$10,MATCH(E3,'Break Register'!$A$2:$A$10,0)),"") | V3: =ABS(M3) | W3: =IF(Q3="MATCHED",0,1)
A4: BALM | B4: BD0058 | C4: JPM 4.0% 2031 | D4: Bond | E4: =A4&"|"&B4 | F4: =IFERROR(INDEX('Internal Book'!$E$2:$E$125,MATCH(E4,'Internal Book'!$H$2:$H$125,0)),0) | G4: =IFERROR(INDEX('Internal Book'!$F$2:$F$125,MATCH(E4,'Internal Book'!$H$2:$H$125,0)),0) | H4: =IFERROR(INDEX('Internal Book'!$G$2:$G$125,MATCH(E4,'Internal Book'!$H$2:$H$125,0)),0) | I4: =IFERROR(INDEX('Custodian Statement'!$E$2:$E$125,MATCH(E4,'Custodian Statement'!$H$2:$H$125,0)),0) | J4: =IFERROR(INDEX('Custodian Statement'!$F$2:$F$125,MATCH(E4,'Custodian Statement'!$H$2:$H$125,0)),0) | K4: =IFERROR(INDEX('Custodian Statement'!$G$2:$G$125,MATCH(E4,'Custodian Statement'!$H$2:$H$125,0)),0) | L4: =F4-I4 | M4: =H4-K4 | N4: =IFERROR((G4-J4)/J4*10000,0) | O4: =COUNTIF('Internal Book'!$H$2:$H$125,E4) | P4: =COUNTIF('Custodian Statement'!$H$2:$H$125,E4) | Q4: =IF(O4=0,"MISSING IN INTERNAL",IF(P4=0,"MISSING IN CUSTODIAN",IF(AND(D4="Cash",ABS(M4)>Parameters!$B$4),"CASH BREAK",IF(L4<>0,"QUANTITY BREAK",IF(ABS(N4)>Parameters!$B$3,"PRICE BREAK",IF(ABS(M4)>Parameters!$B$4,"MV BREAK","MATCHED")))))) | R4: =IFERROR(INDEX('Break Register'!$B$2:$B$10,MATCH(E4,'Break Register'!$A$2:$A$10,0)),"") | S4: =IF(R4="","",Parameters!$B$2-R4) | T4: =IF(S4="","",IF(S4<=2,"0-2 days",IF(S4<=5,"3-5 days",IF(S4<=10,"6-10 days",IF(S4<=30,"11-30 days","30+ days"))))) | U4: =IFERROR(INDEX('Break Register'!$C$2:$C$10,MATCH(E4,'Break Register'!$A$2:$A$10,0)),"") | V4: =ABS(M4) | W4: =IF(Q4="MATCHED",0,1)
A5: BALM | B5: BD0059 | C5: Toyota 2.1% 2027 | D5: Bond | E5: =A5&"|"&B5 | F5: =IFERROR(INDEX('Internal Book'!$E$2:$E$125,MATCH(E5,'Internal Book'!$H$2:$H$125,0)),0) | G5: =IFERROR(INDEX('Internal Book'!$F$2:$F$125,MATCH(E5,'Internal Book'!$H$2:$H$125,0)),0) | H5: =IFERROR(INDEX('Internal Book'!$G$2:$G$125,MATCH(E5,'Internal Book'!$H$2:$H$125,0)),0) | I5: =IFERROR(INDEX('Custodian Statement'!$E$2:$E$125,MATCH(E5,'Custodian Statement'!$H$2:$H$125,0)),0) | J5: =IFERROR(INDEX('Custodian Statement'!$F$2:$F$125,MATCH(E5,'Custodian Statement'!$H$2:$H$125,0)),0) | K5: =IFERROR(INDEX('Custodian Statement'!$G$2:$G$125,MATCH(E5,'Custodian Statement'!$H$2:$H$125,0)),0) | L5: =F5-I5 | M5: =H5-K5 | N5: =IFERROR((G5-J5)/J5*10000,0) | O5: =COUNTIF('Internal Book'!$H$2:$H$125,E5) | P5: =COUNTIF('Custodian Statement'!$H$2:$H$125,E5) | Q5: =IF(O5=0,"MISSING IN INTERNAL",IF(P5=0,"MISSING IN CUSTODIAN",IF(AND(D5="Cash",ABS(M5)>Parameters!$B$4),"CASH BREAK",IF(L5<>0,"QUANTITY BREAK",IF(ABS(N5)>Parameters!$B$3,"PRICE BREAK",IF(ABS(M5)>Parameters!$B$4,"MV BREAK","MATCHED")))))) | R5: =IFERROR(INDEX('Break Register'!$B$2:$B$10,MATCH(E5,'Break Register'!$A$2:$A$10,0)),"") | S5: =IF(R5="","",Parameters!$B$2-R5) | T5: =IF(S5="","",IF(S5<=2,"0-2 days",IF(S5<=5,"3-5 days",IF(S5<=10,"6-10 days",IF(S5<=30,"11-30 days","30+ days"))))) | U5: =IFERROR(INDEX('Break Register'!$C$2:$C$10,MATCH(E5,'Break Register'!$A$2:$A$10,0)),"") | V5: =ABS(M5) | W5: =IF(Q5="MATCHED",0,1)
A6: BALM | B6: BD0061 | C6: Corporate Note Series 01 | D6: Bond | E6: =A6&"|"&B6 | F6: =IFERROR(INDEX('Internal Book'!$E$2:$E$125,MATCH(E6,'Internal Book'!$H$2:$H$125,0)),0) | G6: =IFERROR(INDEX('Internal Book'!$F$2:$F$125,MATCH(E6,'Internal Book'!$H$2:$H$125,0)),0) | H6: =IFERROR(INDEX('Internal Book'!$G$2:$G$125,MATCH(E6,'Internal Book'!$H$2:$H$125,0)),0) | I6: =IFERROR(INDEX('Custodian Statement'!$E$2:$E$125,MATCH(E6,'Custodian Statement'!$H$2:$H$125,0)),0) | J6: =IFERROR(INDEX('Custodian Statement'!$F$2:$F$125,MATCH(E6,'Custodian Statement'!$H$2:$H$125,0)),0) | K6: =IFERROR(INDEX('Custodian Statement'!$G$2:$G$125,MATCH(E6,'Custodian Statement'!$H$2:$H$125,0)),0) | L6: =F6-I6 | M6: =H6-K6 | N6: =IFERROR((G6-J6)/J6*10000,0) | O6: =COUNTIF('Internal Book'!$H$2:$H$125,E6) | P6: =COUNTIF('Custodian Statement'!$H$2:$H$125,E6) | Q6: =IF(O6=0,"MISSING IN INTERNAL",IF(P6=0,"MISSING IN CUSTODIAN",IF(AND(D6="Cash",ABS(M6)>Parameters!$B$4),"CASH BREAK",IF(L6<>0,"QUANTITY BREAK",IF(ABS(N6)>Parameters!$B$3,"PRICE BREAK",IF(ABS(M6)>Parameters!$B$4,"MV BREAK","MATCHED")))))) | R6: =IFERROR(INDEX('Break Register'!$B$2:$B$10,MATCH(E6,'Break Register'!$A$2:$A$10,0)),"") | S6: =IF(R6="","",Parameters!$B$2-R6) | T6: =IF(S6="","",IF(S6<=2,"0-2 days",IF(S6<=5,"3-5 days",IF(S6<=10,"6-10 days",IF(S6<=30,"11-30 days","30+ days"))))) | U6: =IFERROR(INDEX('Break Register'!$C$2:$C$10,MATCH(E6,'Break Register'!$A$2:$A$10,0)),"") | V6: =ABS(M6) | W6: =IF(Q6="MATCHED",0,1)
A7: BALM | B7: BD0064 | C7: Corporate Note Series 04 | D7: Bond | E7: =A7&"|"&B7 | F7: =IFERROR(INDEX('Internal Book'!$E$2:$E$125,MATCH(E7,'Internal Book'!$H$2:$H$125,0)),0) | G7: =IFERROR(INDEX('Internal Book'!$F$2:$F$125,MATCH(E7,'Internal Book'!$H$2:$H$125,0)),0) | H7: =IFERROR(INDEX('Internal Book'!$G$2:$G$125,MATCH(E7,'Internal Book'!$H$2:$H$125,0)),0) | I7: =IFERROR(INDEX('Custodian Statement'!$E$2:$E$125,MATCH(E7,'Custodian Statement'!$H$2:$H$125,0)),0) | J7: =IFERROR(INDEX('Custodian Statement'!$F$2:$F$125,MATCH(E7,'Custodian Statement'!$H$2:$H$125,0)),0) | K7: =IFERROR(INDEX('Custodian Statement'!$G$2:$G$125,MATCH(E7,'Custodian Statement'!$H$2:$H$125,0)),0) | L7: =F7-I7 | M7: =H7-K7 | N7: =IFERROR((G7-J7)/J7*10000,0) | O7: =COUNTIF('Internal Book'!$H$2:$H$125,E7) | P7: =COUNTIF('Custodian Statement'!$H$2:$H$125,E7) | Q7: =IF(O7=0,"MISSING IN INTERNAL",IF(P7=0,"MISSING IN CUSTODIAN",IF(AND(D7="Cash",ABS(M7)>Parameters!$B$4),"CASH BREAK",IF(L7<>0,"QUANTITY BREAK",IF(ABS(N7)>Parameters!$B$3,"PRICE BREAK",IF(ABS(M7)>Parameters!$B$4,"MV BREAK","MATCHED")))))) | R7: =IFERROR(INDEX('Break Register'!$B$2:$B$10,MATCH(E7,'Break Register'!$A$2:$A$10,0)),"") | S7: =IF(R7="","",Parameters!$B$2-R7) | T7: =IF(S7="","",IF(S7<=2,"0-2 days",IF(S7<=5,"3-5 days",IF(S7<=10,"6-10 days",IF(S7<=30,"11-30 days","30+ days"))))) | U7: =IFERROR(INDEX('Break Register'!$C$2:$C$10,MATCH(E7,'Break Register'!$A$2:$A$10,0)),"") | V7: =ABS(M7) | W7: =IF(Q7="MATCHED",0,1)
A8: BALM | B8: BD0066 | C8: Corporate Note Series 06 | D8: Bond | E8: =A8&"|"&B8 | F8: =IFERROR(INDEX('Internal Book'!$E$2:$E$125,MATCH(E8,'Internal Book'!$H$2:$H$125,0)),0) | G8: =IFERROR(INDEX('Internal Book'!$F$2:$F$125,MATCH(E8,'Internal Book'!$H$2:$H$125,0)),0) | H8: =IFERROR(INDEX('Internal Book'!$G$2:$G$125,MATCH(E8,'Internal Book'!$H$2:$H$125,0)),0) | I8: =IFERROR(INDEX('Custodian Statement'!$E$2:$E$125,MATCH(E8,'Custodian Statement'!$H$2:$H$125,0)),0) | J8: =IFERROR(INDEX('Custodian Statement'!$F$2:$F$125,MATCH(E8,'Custodian Statement'!$H$2:$H$125,0)),0) | K8: =IFERROR(INDEX('Custodian Statement'!$G$2:$G$125,MATCH(E8,'Custodian Statement'!$H$2:$H$125,0)),0) | L8: =F8-I8 | M8: =H8-K8 | N8: =IFERROR((G8-J8)/J8*10000,0) | O8: =COUNTIF('Internal Book'!$H$2:$H$125,E8) | P8: =COUNTIF('Custodian Statement'!$H$2:$H$125,E8) | Q8: =IF(O8=0,"MISSING IN INTERNAL",IF(P8=0,"MISSING IN CUSTODIAN",IF(AND(D8="Cash",ABS(M8)>Parameters!$B$4),"CASH BREAK",IF(L8<>0,"QUANTITY BREAK",IF(ABS(N8)>Parameters!$B$3,"PRICE BREAK",IF(ABS(M8)>Parameters!$B$4,"MV BREAK","MATCHED")))))) | R8: =IFERROR(INDEX('Break Register'!$B$2:$B$10,MATCH(E8,'Break Register'!$A$2:$A$10,0)),"") | S8: =IF(R8="","",Parameters!$B$2-R8) | T8: =IF(S8="","",IF(S8<=2,"0-2 days",IF(S8<=5,"3-5 days",IF(S8<=10,"6-10 days",IF(S8<=30,"11-30 days","30+ days"))))) | U8: =IFERROR(INDEX('Break Register'!$C$2:$C$10,MATCH(E8,'Break Register'!$A$2:$A$10,0)),"") | V8: =ABS(M8) | W8: =IF(Q8="MATCHED",0,1)
A9: BALM | B9: BD0070 | C9: Corporate Note Series 10 | D9: Bond | E9: =A9&"|"&B9 | F9: =IFERROR(INDEX('Internal Book'!$E$2:$E$125,MATCH(E9,'Internal Book'!$H$2:$H$125,0)),0) | G9: =IFERROR(INDEX('Internal Book'!$F$2:$F$125,MATCH(E9,'Internal Book'!$H$2:$H$125,0)),0) | H9: =IFERROR(INDEX('Internal Book'!$G$2:$G$125,MATCH(E9,'Internal Book'!$H$2:$H$125,0)),0) | I9: =IFERROR(INDEX('Custodian Statement'!$E$2:$E$125,MATCH(E9,'Custodian Statement'!$H$2:$H$125,0)),0) | J9: =IFERROR(INDEX('Custodian Statement'!$F$2:$F$125,MATCH(E9,'Custodian Statement'!$H$2:$H$125,0)),0) | K9: =IFERROR(INDEX('Custodian Statement'!$G$2:$G$125,MATCH(E9,'Custodian Statement'!$H$2:$H$125,0)),0) | L9: =F9-I9 | M9: =H9-K9 | N9: =IFERROR((G9-J9)/J9*10000,0) | O9: =COUNTIF('Internal Book'!$H$2:$H$125,E9) | P9: =COUNTIF('Custodian Statement'!$H$2:$H$125,E9) | Q9: =IF(O9=0,"MISSING IN INTERNAL",IF(P9=0,"MISSING IN CUSTODIAN",IF(AND(D9="Cash",ABS(M9)>Parameters!$B$4),"CASH BREAK",IF(L9<>0,"QUANTITY BREAK",IF(ABS(N9)>Parameters!$B$3,"PRICE BREAK",IF(ABS(M9)>Parameters!$B$4,"MV BREAK","MATCHED")))))) | R9: =IFERROR(INDEX('Break Register'!$B$2:$B$10,MATCH(E9,'Break Register'!$A$2:$A$10,0)),"") | S9: =IF(R9="","",Parameters!$B$2-R9) | T9: =IF(S9="","",IF(S9<=2,"0-2 days",IF(S9<=5,"3-5 days",IF(S9<=10,"6-10 days",IF(S9<=30,"11-30 days","30+ days"))))) | U9: =IFERROR(INDEX('Break Register'!$C$2:$C$10,MATCH(E9,'Break Register'!$A$2:$A$10,0)),"") | V9: =ABS(M9) | W9: =IF(Q9="MATCHED",0,1)
A10: BALM | B10: BD0074 | C10: Corporate Note Series 14 | D10: Bond | E10: =A10&"|"&B10 | F10: =IFERROR(INDEX('Internal Book'!$E$2:$E$125,MATCH(E10,'Internal Book'!$H$2:$H$125,0)),0) | G10: =IFERROR(INDEX('Internal Book'!$F$2:$F$125,MATCH(E10,'Internal Book'!$H$2:$H$125,0)),0) | H10: =IFERROR(INDEX('Internal Book'!$G$2:$G$125,MATCH(E10,'Internal Book'!$H$2:$H$125,0)),0) | I10: =IFERROR(INDEX('Custodian Statement'!$E$2:$E$125,MATCH(E10,'Custodian Statement'!$H$2:$H$125,0)),0) | J10: =IFERROR(INDEX('Custodian Statement'!$F$2:$F$125,MATCH(E10,'Custodian Statement'!$H$2:$H$125,0)),0) | K10: =IFERROR(INDEX('Custodian Statement'!$G$2:$G$125,MATCH(E10,'Custodian Statement'!$H$2:$H$125,0)),0) | L10: =F10-I10 | M10: =H10-K10 | N10: =IFERROR((G10-J10)/J10*10000,0) | O10: =COUNTIF('Internal Book'!$H$2:$H$125,E10) | P10: =COUNTIF('Custodian Statement'!$H$2:$H$125,E10) | Q10: =IF(O10=0,"MISSING IN INTERNAL",IF(P10=0,"MISSING IN CUSTODIAN",IF(AND(D10="Cash",ABS(M10)>Parameters!$B$4),"CASH BREAK",IF(L10<>0,"QUANTITY BREAK",IF(ABS(N10)>Parameters!$B$3,"PRICE BREAK",IF(ABS(M10)>Parameters!$B$4,"MV BREAK","MATCHED")))))) | R10: =IFERROR(INDEX('Break Register'!$B$2:$B$10,MATCH(E10,'Break Register'!$A$2:$A$10,0)),"") | S10: =IF(R10="","",Parameters!$B$2-R10) | T10: =IF(S10="","",IF(S10<=2,"0-2 days",IF(S10<=5,"3-5 days",IF(S10<=10,"6-10 days",IF(S10<=30,"11-30 days","30+ days"))))) | U10: =IFERROR(INDEX('Break Register'!$C$2:$C$10,MATCH(E10,'Break Register'!$A$2:$A$10,0)),"") | V10: =ABS(M10) | W10: =IF(Q10="MATCHED",0,1)
A11: BALM | B11: BD0075 | C11: Corporate Note Series 15 | D11: Bond | E11: =A11&"|"&B11 | F11: =IFERROR(INDEX('Internal Book'!$E$2:$E$125,MATCH(E11,'Internal Book'!$H$2:$H$125,0)),0) | G11: =IFERROR(INDEX('Internal Book'!$F$2:$F$125,MATCH(E11,'Internal Book'!$H$2:$H$125,0)),0) | H11: =IFERROR(INDEX('Internal Book'!$G$2:$G$125,MATCH(E11,'Internal Book'!$H$2:$H$125,0)),0) | I11: =IFERROR(INDEX('Custodian Statement'!$E$2:$E$125,MATCH(E11,'Custodian Statement'!$H$2:$H$125,0)),0) | J11: =IFERROR(INDEX('Custodian Statement'!$F$2:$F$125,MATCH(E11,'Custodian Statement'!$H$2:$H$125,0)),0) | K11: =IFERROR(INDEX('Custodian Statement'!$G$2:$G$125,MATCH(E11,'Custodian Statement'!$H$2:$H$125,0)),0) | L11: =F11-I11 | M11: =H11-K11 | N11: =IFERROR((G11-J11)/J11*10000,0) | O11: =COUNTIF('Internal Book'!$H$2:$H$125,E11) | P11: =COUNTIF('Custodian Statement'!$H$2:$H$125,E11) | Q11: =IF(O11=0,"MISSING IN INTERNAL",IF(P11=0,"MISSING IN CUSTODIAN",IF(AND(D11="Cash",ABS(M11)>Parameters!$B$4),"CASH BREAK",IF(L11<>0,"QUANTITY BREAK",IF(ABS(N11)>Parameters!$B$3,"PRICE BREAK",IF(ABS(M11)>Parameters!$B$4,"MV BREAK","MATCHED")))))) | R11: =IFERROR(INDEX('Break Register'!$B$2:$B$10,MATCH(E11,'Break Register'!$A$2:$A$10,0)),"") | S11: =IF(R11="","",Parameters!$B$2-R11) | T11: =IF(S11="","",IF(S11<=2,"0-2 days",IF(S11<=5,"3-5 days",IF(S11<=10,"6-10 days",IF(S11<=30,"11-30 days","30+ days"))))) | U11: =IFERROR(INDEX('Break Register'!$C$2:$C$10,MATCH(E11,'Break Register'!$A$2:$A$10,0)),"") | V11: =ABS(M11) | W11: =IF(Q11="MATCHED",0,1)
A12: BALM | B12: BD0076 | C12: Corporate Note Series 16 | D12: Bond | E12: =A12&"|"&B12 | F12: =IFERROR(INDEX('Internal Book'!$E$2:$E$125,MATCH(E12,'Internal Book'!$H$2:$H$125,0)),0) | G12: =IFERROR(INDEX('Internal Book'!$F$2:$F$125,MATCH(E12,'Internal Book'!$H$2:$H$125,0)),0) | H12: =IFERROR(INDEX('Internal Book'!$G$2:$G$125,MATCH(E12,'Internal Book'!$H$2:$H$125,0)),0) | I12: =IFERROR(INDEX('Custodian Statement'!$E$2:$E$125,MATCH(E12,'Custodian Statement'!$H$2:$H$125,0)),0) | J12: =IFERROR(INDEX('Custodian Statement'!$F$2:$F$125,MATCH(E12,'Custodian Statement'!$H$2:$H$125,0)),0) | K12: =IFERROR(INDEX('Custodian Statement'!$G$2:$G$125,MATCH(E12,'Custodian Statement'!$H$2:$H$125,0)),0) | L12: =F12-I12 | M12: =H12-K12 | N12: =IFERROR((G12-J12)/J12*10000,0) | O12: =COUNTIF('Internal Book'!$H$2:$H$125,E12) | P12: =COUNTIF('Custodian Statement'!$H$2:$H$125,E12) | Q12: =IF(O12=0,"MISSING IN INTERNAL",IF(P12=0,"MISSING IN CUSTODIAN",IF(AND(D12="Cash",ABS(M12)>Parameters!$B$4),"CASH BREAK",IF(L12<>0,"QUANTITY BREAK",IF(ABS(N12)>Parameters!$B$3,"PRICE BREAK",IF(ABS(M12)>Parameters!$B$4,"MV BREAK","MATCHED")))))) | R12: =IFERROR(INDEX('Break Register'!$B$2:$B$10,MATCH(E12,'Break Register'!$A$2:$A$10,0)),"") | S12: =IF(R12="","",Parameters!$B$2-R12) | T12: =IF(S12="","",IF(S12<=2,"0-2 days",IF(S12<=5,"3-5 days",IF(S12<=10,"6-10 days",IF(S12<=30,"11-30 days","30+ days"))))) | U12: =IFERROR(INDEX('Break Register'!$C$2:$C$10,MATCH(E12,'Break Register'!$A$2:$A$10,0)),"") | V12: =ABS(M12) | W12: =IF(Q12="MATCHED",0,1)
A13: BALM | B13: BD0080 | C13: Corporate Note Series 20 | D13: Bond | E13: =A13&"|"&B13 | F13: =IFERROR(INDEX('Internal Book'!$E$2:$E$125,MATCH(E13,'Internal Book'!$H$2:$H$125,0)),0) | G13: =IFERROR(INDEX('Internal Book'!$F$2:$F$125,MATCH(E13,'Internal Book'!$H$2:$H$125,0)),0) | H13: =IFERROR(INDEX('Internal Book'!$G$2:$G$125,MATCH(E13,'Internal Book'!$H$2:$H$125,0)),0) | I13: =IFERROR(INDEX('Custodian Statement'!$E$2:$E$125,MATCH(E13,'Custodian Statement'!$H$2:$H$125,0)),0) | J13: =IFERROR(INDEX('Custodian Statement'!$F$2:$F$125,MATCH(E13,'Custodian Statement'!$H$2:$H$125,0)),0) | K13: =IFERROR(INDEX('Custodian Statement'!$G$2:$G$125,MATCH(E13,'Custodian Statement'!$H$2:$H$125,0)),0) | L13: =F13-I13 | M13: =H13-K13 | N13: =IFERROR((G13-J13)/J13*10000,0) | O13: =COUNTIF('Internal Book'!$H$2:$H$125,E13) | P13: =COUNTIF('Custodian Statement'!$H$2:$H$125,E13) | Q13: =IF(O13=0,"MISSING IN INTERNAL",IF(P13=0,"MISSING IN CUSTODIAN",IF(AND(D13="Cash",ABS(M13)>Parameters!$B$4),"CASH BREAK",IF(L13<>0,"QUANTITY BREAK",IF(ABS(N13)>Parameters!$B$3,"PRICE BREAK",IF(ABS(M13)>Parameters!$B$4,"MV BREAK","MATCHED")))))) | R13: =IFERROR(INDEX('Break Register'!$B$2:$B$10,MATCH(E13,'Break Register'!$A$2:$A$10,0)),"") | S13: =IF(R13="","",Parameters!$B$2-R13) | T13: =IF(S13="","",IF(S13<=2,"0-2 days",IF(S13<=5,"3-5 days",IF(S13<=10,"6-10 days",IF(S13<=30,"11-30 days","30+ days"))))) | U13: =IFERROR(INDEX('Break Register'!$C$2:$C$10,MATCH(E13,'Break Register'!$A$2:$A$10,0)),"") | V13: =ABS(M13) | W13: =IF(Q13="MATCHED",0,1)
... A127: MMUS | B127: ET0084 | C127: iShares EUR Corp Bond | D127: ETF | E127: =A127&"|"&B127 | F127: =IFERROR(INDEX('Internal Book'!$E$2:$E$125,MATCH(E127,'Internal Book'!$H$2:$H$125,0)),0) | G127: =IFERROR(INDEX('Internal Book'!$F$2:$F$125,MATCH(E127,'Internal Book'!$H$2:$H$125,0)),0) | H127: =IFERROR(INDEX('Internal Book'!$G$2:$G$125,MATCH(E127,'Internal Book'!$H$2:$H$125,0)),0) | I127: =IFERROR(INDEX('Custodian Statement'!$E$2:$E$125,MATCH(E127,'Custodian Statement'!$H$2:$H$125,0)),0) | J127: =IFERROR(INDEX('Custodian Statement'!$F$2:$F$125,MATCH(E127,'Custodian Statement'!$H$2:$H$125,0)),0) | K127: =IFERROR(INDEX('Custodian Statement'!$G$2:$G$125,MATCH(E127,'Custodian Statement'!$H$2:$H$125,0)),0) | L127: =F127-I127 | M127: =H127-K127 | N127: =IFERROR((G127-J127)/J127*10000,0) | O127: =COUNTIF('Internal Book'!$H$2:$H$125,E127) | P127: =COUNTIF('Custodian Statement'!$H$2:$H$125,E127) | Q127: =IF(O127=0,"MISSING IN INTERNAL",IF(P127=0,"MISSING IN CUSTODIAN",IF(AND(D127="Cash",ABS(M127)>Parameters!$B$4),"CASH BREAK",IF(L127<>0,"QUANTITY BREAK",IF(ABS(N127)>Parameters!$B$3,"PRICE BREAK",IF(ABS(M127)>Parameters!$B$4,"MV BREAK","MATCHED")))))) | R127: =IFERROR(INDEX('Break Register'!$B$2:$B$10,MATCH(E127,'Break Register'!$A$2:$A$10,0)),"") | S127: =IF(R127="","",Parameters!$B$2-R127) | T127: =IF(S127="","",IF(S127<=2,"0-2 days",IF(S127<=5,"3-5 days",IF(S127<=10,"6-10 days",IF(S127<=30,"11-30 days","30+ days"))))) | U127: =IFERROR(INDEX('Break Register'!$C$2:$C$10,MATCH(E127,'Break Register'!$A$2:$A$10,0)),"") | V127: =ABS(M127) | W127: =IF(Q127="MATCHED",0,1)

Sheet Dashboard
A1: Reconciliation Dashboard
A2: As-of 30 Jun 2026 | 4 funds | internal book vs custodian
A4: Positions reconciled | C4: Open breaks | E4: Match rate | G4: Break MV exposure
A5: =COUNTA('Reconciliation'!$E$2:$E$127) | C5: =SUM('Reconciliation'!$W$2:$W$127) | E5: =1-SUM('Reconciliation'!$W$2:$W$127)/COUNTA('Reconciliation'!$E$2:$E$127) | G5: =SUMIFS('Reconciliation'!$V$2:$V$127,'Reconciliation'!$W$2:$W$127,1)
A8: Breaks by type | D8: Break aging | G8: Breaks by fund
A9: Type | B9: Count | D9: Age bucket | E9: Count | G9: Fund | H9: Breaks
A10: MISSING IN INTERNAL | B10: =COUNTIF('Reconciliation'!$Q$2:$Q$127,"MISSING IN INTERNAL") | D10: 0-2 days | E10: =COUNTIF('Reconciliation'!$T$2:$T$127,"0-2 days") | G10: EQGL | H10: =SUMIFS('Reconciliation'!$W$2:$W$127,'Reconciliation'!$A$2:$A$127,G10)
A11: MISSING IN CUSTODIAN | B11: =COUNTIF('Reconciliation'!$Q$2:$Q$127,"MISSING IN CUSTODIAN") | D11: 3-5 days | E11: =COUNTIF('Reconciliation'!$T$2:$T$127,"3-5 days") | G11: FIIG | H11: =SUMIFS('Reconciliation'!$W$2:$W$127,'Reconciliation'!$A$2:$A$127,G11)
A12: QUANTITY BREAK | B12: =COUNTIF('Reconciliation'!$Q$2:$Q$127,"QUANTITY BREAK") | D12: 6-10 days | E12: =COUNTIF('Reconciliation'!$T$2:$T$127,"6-10 days") | G12: BALM | H12: =SUMIFS('Reconciliation'!$W$2:$W$127,'Reconciliation'!$A$2:$A$127,G12)
A13: PRICE BREAK | B13: =COUNTIF('Reconciliation'!$Q$2:$Q$127,"PRICE BREAK") | D13: 11-30 days | E13: =COUNTIF('Reconciliation'!$T$2:$T$127,"11-30 days") | G13: MMUS | H13: =SUMIFS('Reconciliation'!$W$2:$W$127,'Reconciliation'!$A$2:$A$127,G13)
A14: CASH BREAK | B14: =COUNTIF('Reconciliation'!$Q$2:$Q$127,"CASH BREAK") | D14: 30+ days | E14: =COUNTIF('Reconciliation'!$T$2:$T$127,"30+ days")
A15: MV BREAK | B15: =COUNTIF('Reconciliation'!$Q$2:$Q$127,"MV BREAK")
